{
    "type": "minecraft:crafting_shaped",
    "pattern": [
        "###",
        "/X/",
        "OCO"
    ],
    "key": {
        "#": {
            "tag": "forge:ingots/iron"
        },
        "/": {
            "tag": "forge:ingots/redstone_alloy"
        },
        "X": {
            "tag": "forge:ingots/gold"
        },
        "O": {
            "item": "minecraft:smooth_stone"
        },
        "C": {
            "item": "silents_mechanisms:circuit_board"
        }
    },
    "result": {
        "item": "silents_mechanisms:electric_furnace"
    }
}