{
  "parent": "minecraft:recipes/root",
  "rewards": {
    "recipes": [
      "silents_mechanisms:smelting/platinum_ingot_from_dust"
    ]
  },
  "criteria": {
    "get_item": {
      "trigger": "minecraft:inventory_changed",
      "conditions": {
        "items": [
          {
            "tag": "forge:dusts/platinum"
          }
        ]
      }
    },
    "has_the_recipe": {
      "trigger": "minecraft:recipe_unlocked",
      "conditions": {
        "recipe": "silents_mechanisms:smelting/platinum_ingot_from_dust"
      }
    }
  },
  "requirements": [
    [
      "get_item",
      "has_the_recipe"
    ]
  ]
}